{
  "org:founded_by": 12,
  "no_relation": 111,
  "per:employee_of": 12,
  "org:alternate_names": 12,
  "per:cities_of_residence": 12,
  "per:children": 12,
  "per:title": 12,
  "per:siblings": 12,
  "per:religion": 6,
  "per:age": 12,
  "org:website": 12,
  "per:stateorprovinces_of_residence": 12,
  "org:member_of": 12,
  "org:top_members/employees": 12,
  "per:countries_of_residence": 12,
  "org:city_of_headquarters": 12,
  "org:members": 12,
  "org:country_of_headquarters": 12,
  "per:spouse": 12,
  "org:stateorprovince_of_headquarters": 12,
  "org:number_of_employees/members": 9,
  "org:parents": 12,
  "org:subsidiaries": 12,
  "per:origin": 12,
  "org:political/religious_affiliation": 12,
  "per:other_family": 12,
  "per:stateorprovince_of_birth": 5,
  "org:dissolved": 3,
  "per:date_of_death": 12,
  "org:shareholders": 9,
  "per:alternate_names": 12,
  "per:parents": 12,
  "per:schools_attended": 12,
  "per:cause_of_death": 12,
  "per:city_of_death": 9,
  "per:stateorprovince_of_death": 6,
  "org:founded": 11,
  "per:country_of_birth": 4,
  "per:date_of_birth": 7,
  "per:city_of_birth": 8,
  "per:charges": 8,
  "per:country_of_death": 1
}
